aiopylimit/__init__.py
aiopylimit/aiopyratelimit.py
aiopylimit/aiopyratelimit_exception.py
aiopylimit/aioredis_helper.py
aiopylimit-0.2.2.dist-info/LICENSE.txt
aiopylimit-0.2.2.dist-info/METADATA
aiopylimit-0.2.2.dist-info/WHEEL
aiopylimit-0.2.2.dist-info/top_level.txt
aiopylimit-0.2.2.dist-info/RECORD
