Metadata-Version: 2.1
Name: aiopylimit
Version: 0.2.2
Summary: A distributed rate limiting library for python using leaky bucket algorithm and Redis(asyncio version)
Home-page: https://github.com/dmarkey/aiopylimit
Author: David Markey
Author-email: david@dmarkey.com
Keywords: rate limiting,throttle,redis,asyncio
License-File: LICENSE.txt
Requires-Dist: aioredis (<=1.1.0)
